aether/__init__.py
aether/cli.py
aether/config.py
aether/models/__init__.py
aether/models/base.py
aether/models/gemini.py
aether/models/gpt.py
aether/models/kimi.py
aether/models/qwen.py
aether/models/spark.py
aether_cli-0.1.0.dist-info/LICENSE
aether_cli-0.1.0.dist-info/METADATA
aether_cli-0.1.0.dist-info/WHEEL
aether_cli-0.1.0.dist-info/entry_points.txt
aether_cli-0.1.0.dist-info/top_level.txt
aether_cli-0.1.0.dist-info/RECORD
